google_patents_mcp/__init__.py
google_patents_mcp/__main__.py
google_patents_mcp/client.py
google_patents_mcp/server.py
mcp_server_google_patents-0.1.6.dist-info/METADATA
mcp_server_google_patents-0.1.6.dist-info/WHEEL
mcp_server_google_patents-0.1.6.dist-info/entry_points.txt
mcp_server_google_patents-0.1.6.dist-info/RECORD
