Metadata-Version: 2.4
Name: mcp-server-google-patents
Version: 0.1.6
Summary: MCP server for Google Patents via SerpApi
Author-email: Antigravity <antigravity@example.com>
License-Expression: MIT
Requires-Python: >=3.10
Requires-Dist: mcp
Requires-Dist: python-dotenv
Requires-Dist: requests
